{
  "annotations": {
    "changelogDate": "20260612010952"
  },
  "applications": ["*"],
  "dto": "mapstruct",
  "fields": [
    {
      "fieldName": "address",
      "fieldType": "String",
      "fieldValidateRules": ["required", "maxlength"],
      "fieldValidateRulesMaxlength": "150"
    },
    {
      "fieldName": "city",
      "fieldType": "String",
      "fieldValidateRules": ["required", "maxlength"],
      "fieldValidateRulesMaxlength": "80"
    },
    {
      "fieldName": "loyaltyPoints",
      "fieldType": "Integer",
      "fieldValidateRules": ["min"],
      "fieldValidateRulesMin": "0"
    },
    {
      "fieldName": "verified",
      "fieldType": "Boolean",
      "fieldValidateRules": ["required"]
    }
  ],
  "jpaMetamodelFiltering": true,
  "name": "CustomerProfile",
  "pagination": "pagination",
  "relationships": [
    {
      "otherEntityName": "customer",
      "otherEntityRelationshipName": "profile",
      "relationshipName": "customer",
      "relationshipSide": "left",
      "relationshipType": "one-to-one",
      "relationshipValidateRules": "required"
    }
  ],
  "searchEngine": "no",
  "service": "serviceClass"
}
